calculator_alespool.py
calculator_alespool-0.1.1.dist-info/LICENSE
calculator_alespool-0.1.1.dist-info/WHEEL
calculator_alespool-0.1.1.dist-info/METADATA
calculator_alespool-0.1.1.dist-info/RECORD
