Metadata-Version: 2.1
Name: calculator_alespool
Version: 0.1.1
Summary: Creating a calculator that can be used to add, subtract, multiply, divide and take (n) root power
Author-email: Alessio Nespoli <alessionespoli.97@gmail.com>
Requires-Python: >=3.7
Classifier: Programming Language :: Python :: 3
Classifier: License :: OSI Approved :: MIT License
Classifier: Operating System :: OS Independent
Project-URL: Home, https://github.com/TuringCollegeSubmissions/anespo-DWWP.1.git
